{
    "app_key": "b0l2ndgk_8EhVZB57aTPfj83NP9YTVP8yBH4AkxSg",
    "billing_type": "gb_per_day",
    "cluster": "test01",
    "cold_storage": "3",
    "cold_storage_days": "0",
    "consumer_amount": "1200",
    "consumer_type": "user",
    "disk_space": "0",
    "end_date": "2024-10-31 23:59:59",
    "eps": "",
    "eps_percent": "",
    "events_per_day": "0",
    "expiry_action": "warn",
    "features": {
      "ATS": "No",
      "Autonomous Threat Sweeper Service - threat assessment and response": "No",
      "Additional Cold storage": "6-days",
      "Additional Hot storage": "1-day",
      "Advanced Behavioral Analytics": "No",
      "Advanced Threat Modeling: Behavioral profiling of threats": "No",
      "Basic Analytics - IEE and AEE": "Yes",
      "Basic Threat Modeling: Map policies to attack chain": "No",
      "Content / Data Science Studio (Premium playbooks and usage are metered)": "Yes",
      "Data Services (Hydration, handover)": "Yes",
      "Data Storage with Snowflake Data Lake": "90-days",
      "Data enrichment: Threat Intelligence, Geolocation, Identity": "Yes",
      "Hosted (Cloud) Collectors": "No",
      "Investigate: Integrate internal and external data in investigation process": "Yes",
      "Monthly search capacity included with the package": "10x",
      "NxLog Windows data collection": "No",
      "Premium Data enrichment: IP attribution": "No",
      "Premium Disaster Recovery: Improved recovery and availability SLAs": "Yes",
      "SOAR: Security Orchestration and Automation and Response module": "Lite",
      "Standard Behavioral Analytics": "No",
      "Threat Coverage Analyzer: Security posture assessment": "Yes"
    },
    "gb_per_day": "50-100",
    "grace_period": "20-days",
    "holder": "SECURONIX",
    "issued_on": 1726041547414,
    "issuer": "SECURONIX",
    "jira_ticket": "testtiicket",
    "license_type": "mssp",
    "licensed_resources": "1000000000",
    "licensed_users": "1000",
    "lifecycle_status": "noworries",
    "name": "Saurabh Soni",
    "operation": "generate_license",
    "plan": "basic",
    "policy_allowed_count": "1500",
    "start_date": "2024-09-11 00:00:00",
    "status": "valid",
    "tenant_id": "test01",
    "tenantname": "test01",
    "useremail": null,
    "validity": "51-days",
    "version": "version1.0",
    "warn_period": "60-days"
  }
  